{"id": 84665539, "node_id": "MDEwOlJlcG9zaXRvcnk4NDY2NTUzOQ==", "name": "Cake.Prca.PullRequests.Tfs", "full_name": "cake-contrib/Cake.Prca.PullRequests.Tfs", "private": false, "owner": {"login": "cake-contrib", "id": 21088753, "node_id": "MDEyOk9yZ2FuaXphdGlvbjIxMDg4NzUz", "avatar_url": "https://avatars.githubusercontent.com/u/21088753?v=4", "gravatar_id": "", "url": "https://api.github.com/users/cake-contrib", "html_url": "https://github.com/cake-contrib", "followers_url": "https://api.github.com/users/cake-contrib/followers", "following_url": "https://api.github.com/users/cake-contrib/following{/other_user}", "gists_url": "https://api.github.com/users/cake-contrib/gists{/gist_id}", "starred_url": "https://api.github.com/users/cake-contrib/starred{/owner}{/repo}", "subscriptions_url": "https://api.github.com/users/cake-contrib/subscriptions", "organizations_url": "https://api.github.com/users/cake-contrib/orgs", "repos_url": "https://api.github.com/users/cake-contrib/repos", "events_url": "https://api.github.com/users/cake-contrib/events{/privacy}", "received_events_url": "https://api.github.com/users/cake-contrib/received_events", "type": "Organization", "site_admin": false}, "html_url": "https://github.com/cake-contrib/Cake.Prca.PullRequests.Tfs", "description": "Support for writing issues to TFS or VSTS using the Cake.Prca addin", "fork": false, "url": "https://api.github.com/repos/cake-contrib/Cake.Prca.PullRequests.Tfs", "forks_url": "https://api.github.com/repos/cake-contrib/Cake.Prca.PullRequests.Tfs/forks", "keys_url": "https://api.github.com/repos/cake-contrib/Cake.Prca.PullRequests.Tfs/keys{/key_id}", "collaborators_url": "https://api.github.com/repos/cake-contrib/Cake.Prca.PullRequests.Tfs/collaborators{/collaborator}", "teams_url": "https://api.github.com/repos/cake-contrib/Cake.Prca.PullRequests.Tfs/teams", "hooks_url": "https://api.github.com/repos/cake-contrib/Cake.Prca.PullRequests.Tfs/hooks", "issue_events_url": "https://api.github.com/repos/cake-contrib/Cake.Prca.PullRequests.Tfs/issues/events{/number}", "events_url": "https://api.github.com/repos/cake-contrib/Cake.Prca.PullRequests.Tfs/events", "assignees_url": "https://api.github.com/repos/cake-contrib/Cake.Prca.PullRequests.Tfs/assignees{/user}", "branches_url": "https://api.github.com/repos/cake-contrib/Cake.Prca.PullRequests.Tfs/branches{/branch}", "tags_url": "https://api.github.com/repos/cake-contrib/Cake.Prca.PullRequests.Tfs/tags", "blobs_url": "https://api.github.com/repos/cake-contrib/Cake.Prca.PullRequests.Tfs/git/blobs{/sha}", "git_tags_url": "https://api.github.com/repos/cake-contrib/Cake.Prca.PullRequests.Tfs/git/tags{/sha}", "git_refs_url": "https://api.github.com/repos/cake-contrib/Cake.Prca.PullRequests.Tfs/git/refs{/sha}", "trees_url": "https://api.github.com/repos/cake-contrib/Cake.Prca.PullRequests.Tfs/git/trees{/sha}", "statuses_url": "https://api.github.com/repos/cake-contrib/Cake.Prca.PullRequests.Tfs/statuses/{sha}", "languages_url": "https://api.github.com/repos/cake-contrib/Cake.Prca.PullRequests.Tfs/languages", "stargazers_url": "https://api.github.com/repos/cake-contrib/Cake.Prca.PullRequests.Tfs/stargazers", "contributors_url": "https://api.github.com/repos/cake-contrib/Cake.Prca.PullRequests.Tfs/contributors", "subscribers_url": "https://api.github.com/repos/cake-contrib/Cake.Prca.PullRequests.Tfs/subscribers", "subscription_url": "https://api.github.com/repos/cake-contrib/Cake.Prca.PullRequests.Tfs/subscription", "commits_url": "https://api.github.com/repos/cake-contrib/Cake.Prca.PullRequests.Tfs/commits{/sha}", "git_commits_url": "https://api.github.com/repos/cake-contrib/Cake.Prca.PullRequests.Tfs/git/commits{/sha}", "comments_url": "https://api.github.com/repos/cake-contrib/Cake.Prca.PullRequests.Tfs/comments{/number}", "issue_comment_url": "https://api.github.com/repos/cake-contrib/Cake.Prca.PullRequests.Tfs/issues/comments{/number}", "contents_url": "https://api.github.com/repos/cake-contrib/Cake.Prca.PullRequests.Tfs/contents/{+path}", "compare_url": "https://api.github.com/repos/cake-contrib/Cake.Prca.PullRequests.Tfs/compare/{base}...{head}", "merges_url": "https://api.github.com/repos/cake-contrib/Cake.Prca.PullRequests.Tfs/merges", "archive_url": "https://api.github.com/repos/cake-contrib/Cake.Prca.PullRequests.Tfs/{archive_format}{/ref}", "downloads_url": "https://api.github.com/repos/cake-contrib/Cake.Prca.PullRequests.Tfs/downloads", "issues_url": "https://api.github.com/repos/cake-contrib/Cake.Prca.PullRequests.Tfs/issues{/number}", "pulls_url": "https://api.github.com/repos/cake-contrib/Cake.Prca.PullRequests.Tfs/pulls{/number}", "milestones_url": "https://api.github.com/repos/cake-contrib/Cake.Prca.PullRequests.Tfs/milestones{/number}", "notifications_url": "https://api.github.com/repos/cake-contrib/Cake.Prca.PullRequests.Tfs/notifications{?since,all,participating}", "labels_url": "https://api.github.com/repos/cake-contrib/Cake.Prca.PullRequests.Tfs/labels{/name}", "releases_url": "https://api.github.com/repos/cake-contrib/Cake.Prca.PullRequests.Tfs/releases{/id}", "deployments_url": "https://api.github.com/repos/cake-contrib/Cake.Prca.PullRequests.Tfs/deployments", "created_at": "2017-03-11T16:54:18Z", "updated_at": "2023-01-28T21:19:33Z", "pushed_at": "2017-12-27T18:01:23Z", "git_url": "git://github.com/cake-contrib/Cake.Prca.PullRequests.Tfs.git", "ssh_url": "git@github.com:cake-contrib/Cake.Prca.PullRequests.Tfs.git", "clone_url": "https://github.com/cake-contrib/Cake.Prca.PullRequests.Tfs.git", "svn_url": "https://github.com/cake-contrib/Cake.Prca.PullRequests.Tfs", "homepage": "https://cake-contrib.github.io/Cake.Prca.Website", "size": 97, "stargazers_count": 1, "watchers_count": 1, "language": "C#", "has_issues": false, "has_projects": false, "has_downloads": true, "has_wiki": false, "has_pages": false, "has_discussions": false, "forks_count": 3, "mirror_url": null, "archived": true, "disabled": false, "open_issues_count": 0, "license": {"key": "other", "name": "Other", "spdx_id": "NOASSERTION", "url": null, "node_id": "MDc6TGljZW5zZTA="}, "allow_forking": true, "is_template": false, "web_commit_signoff_required": false, "topics": ["cake-addin", "cake-build", "cake-prca", "cake-prca-pullrequestsystem", "tfs", "vsts"], "visibility": "public", "forks": 3, "open_issues": 0, "watchers": 1, "default_branch": "develop", "permissions": {"admin": false, "maintain": false, "push": false, "triage": false, "pull": true}, "temp_clone_token": "", "organization": {"login": "cake-contrib", "id": 21088753, "node_id": "MDEyOk9yZ2FuaXphdGlvbjIxMDg4NzUz", "avatar_url": "https://avatars.githubusercontent.com/u/21088753?v=4", "gravatar_id": "", "url": "https://api.github.com/users/cake-contrib", "html_url": "https://github.com/cake-contrib", "followers_url": "https://api.github.com/users/cake-contrib/followers", "following_url": "https://api.github.com/users/cake-contrib/following{/other_user}", "gists_url": "https://api.github.com/users/cake-contrib/gists{/gist_id}", "starred_url": "https://api.github.com/users/cake-contrib/starred{/owner}{/repo}", "subscriptions_url": "https://api.github.com/users/cake-contrib/subscriptions", "organizations_url": "https://api.github.com/users/cake-contrib/orgs", "repos_url": "https://api.github.com/users/cake-contrib/repos", "events_url": "https://api.github.com/users/cake-contrib/events{/privacy}", "received_events_url": "https://api.github.com/users/cake-contrib/received_events", "type": "Organization", "site_admin": false}, "network_count": 3, "subscribers_count": 8}