{"id": 565795918, "node_id": "R_kgDOIblcTg", "name": "GPpyTools", "full_name": "xelarep/GPpyTools", "private": false, "owner": {"login": "xelarep", "id": 34999990, "node_id": "MDQ6VXNlcjM0OTk5OTkw", "avatar_url": "https://avatars.githubusercontent.com/u/34999990?v=4", "gravatar_id": "", "url": "https://api.github.com/users/xelarep", "html_url": "https://github.com/xelarep", "followers_url": "https://api.github.com/users/xelarep/followers", "following_url": "https://api.github.com/users/xelarep/following{/other_user}", "gists_url": "https://api.github.com/users/xelarep/gists{/gist_id}", "starred_url": "https://api.github.com/users/xelarep/starred{/owner}{/repo}", "subscriptions_url": "https://api.github.com/users/xelarep/subscriptions", "organizations_url": "https://api.github.com/users/xelarep/orgs", "repos_url": "https://api.github.com/users/xelarep/repos", "events_url": "https://api.github.com/users/xelarep/events{/privacy}", "received_events_url": "https://api.github.com/users/xelarep/received_events", "type": "User", "site_admin": false}, "html_url": "https://github.com/xelarep/GPpyTools", "description": "Readout of Plugin information from Gig Performer .gig files or Plugin Manager settings", "fork": false, "url": "https://api.github.com/repos/xelarep/GPpyTools", "forks_url": "https://api.github.com/repos/xelarep/GPpyTools/forks", "keys_url": "https://api.github.com/repos/xelarep/GPpyTools/keys{/key_id}", "collaborators_url": "https://api.github.com/repos/xelarep/GPpyTools/collaborators{/collaborator}", "teams_url": "https://api.github.com/repos/xelarep/GPpyTools/teams", "hooks_url": "https://api.github.com/repos/xelarep/GPpyTools/hooks", "issue_events_url": "https://api.github.com/repos/xelarep/GPpyTools/issues/events{/number}", "events_url": "https://api.github.com/repos/xelarep/GPpyTools/events", "assignees_url": "https://api.github.com/repos/xelarep/GPpyTools/assignees{/user}", "branches_url": "https://api.github.com/repos/xelarep/GPpyTools/branches{/branch}", "tags_url": "https://api.github.com/repos/xelarep/GPpyTools/tags", "blobs_url": "https://api.github.com/repos/xelarep/GPpyTools/git/blobs{/sha}", "git_tags_url": "https://api.github.com/repos/xelarep/GPpyTools/git/tags{/sha}", "git_refs_url": "https://api.github.com/repos/xelarep/GPpyTools/git/refs{/sha}", "trees_url": "https://api.github.com/repos/xelarep/GPpyTools/git/trees{/sha}", "statuses_url": "https://api.github.com/repos/xelarep/GPpyTools/statuses/{sha}", "languages_url": "https://api.github.com/repos/xelarep/GPpyTools/languages", "stargazers_url": "https://api.github.com/repos/xelarep/GPpyTools/stargazers", "contributors_url": "https://api.github.com/repos/xelarep/GPpyTools/contributors", "subscribers_url": "https://api.github.com/repos/xelarep/GPpyTools/subscribers", "subscription_url": "https://api.github.com/repos/xelarep/GPpyTools/subscription", "commits_url": "https://api.github.com/repos/xelarep/GPpyTools/commits{/sha}", "git_commits_url": "https://api.github.com/repos/xelarep/GPpyTools/git/commits{/sha}", "comments_url": "https://api.github.com/repos/xelarep/GPpyTools/comments{/number}", "issue_comment_url": "https://api.github.com/repos/xelarep/GPpyTools/issues/comments{/number}", "contents_url": "https://api.github.com/repos/xelarep/GPpyTools/contents/{+path}", "compare_url": "https://api.github.com/repos/xelarep/GPpyTools/compare/{base}...{head}", "merges_url": "https://api.github.com/repos/xelarep/GPpyTools/merges", "archive_url": "https://api.github.com/repos/xelarep/GPpyTools/{archive_format}{/ref}", "downloads_url": "https://api.github.com/repos/xelarep/GPpyTools/downloads", "issues_url": "https://api.github.com/repos/xelarep/GPpyTools/issues{/number}", "pulls_url": "https://api.github.com/repos/xelarep/GPpyTools/pulls{/number}", "milestones_url": "https://api.github.com/repos/xelarep/GPpyTools/milestones{/number}", "notifications_url": "https://api.github.com/repos/xelarep/GPpyTools/notifications{?since,all,participating}", "labels_url": "https://api.github.com/repos/xelarep/GPpyTools/labels{/name}", "releases_url": "https://api.github.com/repos/xelarep/GPpyTools/releases{/id}", "deployments_url": "https://api.github.com/repos/xelarep/GPpyTools/deployments", "created_at": "2022-11-14T10:47:44Z", "updated_at": "2022-11-14T11:24:37Z", "pushed_at": "2022-11-20T16:17:52Z", "git_url": "git://github.com/xelarep/GPpyTools.git", "ssh_url": "git@github.com:xelarep/GPpyTools.git", "clone_url": "https://github.com/xelarep/GPpyTools.git", "svn_url": "https://github.com/xelarep/GPpyTools", "homepage": "", "size": 61436, "stargazers_count": 0, "watchers_count": 0, "language": "Python", "has_issues": true, "has_projects": true, "has_downloads": true, "has_wiki": true, "has_pages": false, "has_discussions": false, "forks_count": 0, "mirror_url": null, "archived": false, "disabled": false, "open_issues_count": 0, "license": null, "allow_forking": true, "is_template": false, "web_commit_signoff_required": false, "topics": ["au", "gigperformer", "vst", "vst3"], "visibility": "public", "forks": 0, "open_issues": 0, "watchers": 0, "default_branch": "main", "permissions": {"admin": false, "maintain": false, "push": false, "triage": false, "pull": true}, "temp_clone_token": "", "network_count": 0, "subscribers_count": 1}