{"id": 444312058, "node_id": "R_kgDOGnup-g", "name": "EIM", "full_name": "EchoInMirror/EIM", "private": false, "owner": {"login": "EchoInMirror", "id": 75782140, "node_id": "MDEyOk9yZ2FuaXphdGlvbjc1NzgyMTQw", "avatar_url": "https://avatars.githubusercontent.com/u/75782140?v=4", "gravatar_id": "", "url": "https://api.github.com/users/EchoInMirror", "html_url": "https://github.com/EchoInMirror", "followers_url": "https://api.github.com/users/EchoInMirror/followers", "following_url": "https://api.github.com/users/EchoInMirror/following{/other_user}", "gists_url": "https://api.github.com/users/EchoInMirror/gists{/gist_id}", "starred_url": "https://api.github.com/users/EchoInMirror/starred{/owner}{/repo}", "subscriptions_url": "https://api.github.com/users/EchoInMirror/subscriptions", "organizations_url": "https://api.github.com/users/EchoInMirror/orgs", "repos_url": "https://api.github.com/users/EchoInMirror/repos", "events_url": "https://api.github.com/users/EchoInMirror/events{/privacy}", "received_events_url": "https://api.github.com/users/EchoInMirror/received_events", "type": "Organization", "site_admin": false}, "html_url": "https://github.com/EchoInMirror/EIM", "description": "A Web Music Production Workstation (DAW) supports VST.", "fork": false, "url": "https://api.github.com/repos/EchoInMirror/EIM", "forks_url": "https://api.github.com/repos/EchoInMirror/EIM/forks", "keys_url": "https://api.github.com/repos/EchoInMirror/EIM/keys{/key_id}", "collaborators_url": "https://api.github.com/repos/EchoInMirror/EIM/collaborators{/collaborator}", "teams_url": "https://api.github.com/repos/EchoInMirror/EIM/teams", "hooks_url": "https://api.github.com/repos/EchoInMirror/EIM/hooks", "issue_events_url": "https://api.github.com/repos/EchoInMirror/EIM/issues/events{/number}", "events_url": "https://api.github.com/repos/EchoInMirror/EIM/events", "assignees_url": "https://api.github.com/repos/EchoInMirror/EIM/assignees{/user}", "branches_url": "https://api.github.com/repos/EchoInMirror/EIM/branches{/branch}", "tags_url": "https://api.github.com/repos/EchoInMirror/EIM/tags", "blobs_url": "https://api.github.com/repos/EchoInMirror/EIM/git/blobs{/sha}", "git_tags_url": "https://api.github.com/repos/EchoInMirror/EIM/git/tags{/sha}", "git_refs_url": "https://api.github.com/repos/EchoInMirror/EIM/git/refs{/sha}", "trees_url": "https://api.github.com/repos/EchoInMirror/EIM/git/trees{/sha}", "statuses_url": "https://api.github.com/repos/EchoInMirror/EIM/statuses/{sha}", "languages_url": "https://api.github.com/repos/EchoInMirror/EIM/languages", "stargazers_url": "https://api.github.com/repos/EchoInMirror/EIM/stargazers", "contributors_url": "https://api.github.com/repos/EchoInMirror/EIM/contributors", "subscribers_url": "https://api.github.com/repos/EchoInMirror/EIM/subscribers", "subscription_url": "https://api.github.com/repos/EchoInMirror/EIM/subscription", "commits_url": "https://api.github.com/repos/EchoInMirror/EIM/commits{/sha}", "git_commits_url": "https://api.github.com/repos/EchoInMirror/EIM/git/commits{/sha}", "comments_url": "https://api.github.com/repos/EchoInMirror/EIM/comments{/number}", "issue_comment_url": "https://api.github.com/repos/EchoInMirror/EIM/issues/comments{/number}", "contents_url": "https://api.github.com/repos/EchoInMirror/EIM/contents/{+path}", "compare_url": "https://api.github.com/repos/EchoInMirror/EIM/compare/{base}...{head}", "merges_url": "https://api.github.com/repos/EchoInMirror/EIM/merges", "archive_url": "https://api.github.com/repos/EchoInMirror/EIM/{archive_format}{/ref}", "downloads_url": "https://api.github.com/repos/EchoInMirror/EIM/downloads", "issues_url": "https://api.github.com/repos/EchoInMirror/EIM/issues{/number}", "pulls_url": "https://api.github.com/repos/EchoInMirror/EIM/pulls{/number}", "milestones_url": "https://api.github.com/repos/EchoInMirror/EIM/milestones{/number}", "notifications_url": "https://api.github.com/repos/EchoInMirror/EIM/notifications{?since,all,participating}", "labels_url": "https://api.github.com/repos/EchoInMirror/EIM/labels{/name}", "releases_url": "https://api.github.com/repos/EchoInMirror/EIM/releases{/id}", "deployments_url": "https://api.github.com/repos/EchoInMirror/EIM/deployments", "created_at": "2022-01-04T06:35:10Z", "updated_at": "2023-08-31T14:22:22Z", "pushed_at": "2022-12-05T12:37:42Z", "git_url": "git://github.com/EchoInMirror/EIM.git", "ssh_url": "git@github.com:EchoInMirror/EIM.git", "clone_url": "https://github.com/EchoInMirror/EIM.git", "svn_url": "https://github.com/EchoInMirror/EIM", "homepage": "", "size": 1746, "stargazers_count": 52, "watchers_count": 52, "language": "TypeScript", "has_issues": true, "has_projects": true, "has_downloads": true, "has_wiki": true, "has_pages": false, "has_discussions": false, "forks_count": 6, "mirror_url": null, "archived": false, "disabled": false, "open_issues_count": 0, "license": {"key": "agpl-3.0", "name": "GNU Affero General Public License v3.0", "spdx_id": "AGPL-3.0", "url": "https://api.github.com/licenses/agpl-3.0", "node_id": "MDc6TGljZW5zZTE="}, "allow_forking": true, "is_template": false, "web_commit_signoff_required": false, "topics": ["au", "daw", "juce", "music", "typescript", "vst", "vst3"], "visibility": "public", "forks": 6, "open_issues": 0, "watchers": 52, "default_branch": "master", "permissions": {"admin": false, "maintain": false, "push": false, "triage": false, "pull": true}, "temp_clone_token": "", "organization": {"login": "EchoInMirror", "id": 75782140, "node_id": "MDEyOk9yZ2FuaXphdGlvbjc1NzgyMTQw", "avatar_url": "https://avatars.githubusercontent.com/u/75782140?v=4", "gravatar_id": "", "url": "https://api.github.com/users/EchoInMirror", "html_url": "https://github.com/EchoInMirror", "followers_url": "https://api.github.com/users/EchoInMirror/followers", "following_url": "https://api.github.com/users/EchoInMirror/following{/other_user}", "gists_url": "https://api.github.com/users/EchoInMirror/gists{/gist_id}", "starred_url": "https://api.github.com/users/EchoInMirror/starred{/owner}{/repo}", "subscriptions_url": "https://api.github.com/users/EchoInMirror/subscriptions", "organizations_url": "https://api.github.com/users/EchoInMirror/orgs", "repos_url": "https://api.github.com/users/EchoInMirror/repos", "events_url": "https://api.github.com/users/EchoInMirror/events{/privacy}", "received_events_url": "https://api.github.com/users/EchoInMirror/received_events", "type": "Organization", "site_admin": false}, "network_count": 6, "subscribers_count": 3}