{"total_count": 1, "incomplete_results": false, "items": [{"url": "https://api.github.com/repos/mvmjacobs/az-devops-rice-extension/issues/1", "repository_url": "https://api.github.com/repos/mvmjacobs/az-devops-rice-extension", "labels_url": "https://api.github.com/repos/mvmjacobs/az-devops-rice-extension/issues/1/labels{/name}", "comments_url": "https://api.github.com/repos/mvmjacobs/az-devops-rice-extension/issues/1/comments", "events_url": "https://api.github.com/repos/mvmjacobs/az-devops-rice-extension/issues/1/events", "html_url": "https://github.com/mvmjacobs/az-devops-rice-extension/issues/1", "id": 1110723967, "node_id": "I_kwDOCVJjm85CNE1_", "number": 1, "title": "Impact field missing in dropdown", "user": {"login": "dotcologne", "id": 8538077, "node_id": "MDQ6VXNlcjg1MzgwNzc=", "avatar_url": "https://avatars.githubusercontent.com/u/8538077?v=4", "gravatar_id": "", "url": "https://api.github.com/users/dotcologne", "html_url": "https://github.com/dotcologne", "followers_url": "https://api.github.com/users/dotcologne/followers", "following_url": "https://api.github.com/users/dotcologne/following{/other_user}", "gists_url": "https://api.github.com/users/dotcologne/gists{/gist_id}", "starred_url": "https://api.github.com/users/dotcologne/starred{/owner}{/repo}", "subscriptions_url": "https://api.github.com/users/dotcologne/subscriptions", "organizations_url": "https://api.github.com/users/dotcologne/orgs", "repos_url": "https://api.github.com/users/dotcologne/repos", "events_url": "https://api.github.com/users/dotcologne/events{/privacy}", "received_events_url": "https://api.github.com/users/dotcologne/received_events", "type": "User", "site_admin": false}, "labels": [], "state": "open", "locked": false, "assignee": null, "assignees": [], "milestone": null, "comments": 0, "created_at": "2022-01-21T17:32:06Z", "updated_at": "2022-01-21T17:32:06Z", "closed_at": null, "author_association": "NONE", "active_lock_reason": null, "body": "I cannot select Impact, there's no such option in the dropdown. However, the field Impact exists, but per default it's stringlist. Please advise, thanks!\r\n\r\n![grafik](https://user-images.githubusercontent.com/8538077/150573013-e6804314-42c2-487b-80ad-7bd796a60d8b.png)\r\n", "reactions": {"url": "https://api.github.com/repos/mvmjacobs/az-devops-rice-extension/issues/1/reactions", "total_count": 0, "+1": 0, "-1": 0, "laugh": 0, "hooray": 0, "confused": 0, "heart": 0, "rocket": 0, "eyes": 0}, "timeline_url": "https://api.github.com/repos/mvmjacobs/az-devops-rice-extension/issues/1/timeline", "performed_via_github_app": null, "state_reason": null, "score": 1.0}]}