[{"login": "xunil-cloud", "id": 59048158, "node_id": "MDQ6VXNlcjU5MDQ4MTU4", "avatar_url": "https://avatars.githubusercontent.com/u/59048158?v=4", "gravatar_id": "", "url": "https://api.github.com/users/xunil-cloud", "html_url": "https://github.com/xunil-cloud", "followers_url": "https://api.github.com/users/xunil-cloud/followers", "following_url": "https://api.github.com/users/xunil-cloud/following{/other_user}", "gists_url": "https://api.github.com/users/xunil-cloud/gists{/gist_id}", "starred_url": "https://api.github.com/users/xunil-cloud/starred{/owner}{/repo}", "subscriptions_url": "https://api.github.com/users/xunil-cloud/subscriptions", "organizations_url": "https://api.github.com/users/xunil-cloud/orgs", "repos_url": "https://api.github.com/users/xunil-cloud/repos", "events_url": "https://api.github.com/users/xunil-cloud/events{/privacy}", "received_events_url": "https://api.github.com/users/xunil-cloud/received_events", "type": "User", "site_admin": false, "contributions": 91}]