{"total_count": 1, "incomplete_results": false, "items": [{"url": "https://api.github.com/repos/osowskit/microsoft-github-app-extension/issues/1", "repository_url": "https://api.github.com/repos/osowskit/microsoft-github-app-extension", "labels_url": "https://api.github.com/repos/osowskit/microsoft-github-app-extension/issues/1/labels{/name}", "comments_url": "https://api.github.com/repos/osowskit/microsoft-github-app-extension/issues/1/comments", "events_url": "https://api.github.com/repos/osowskit/microsoft-github-app-extension/issues/1/events", "html_url": "https://github.com/osowskit/microsoft-github-app-extension/pull/1", "id": 248113970, "node_id": "MDExOlB1bGxSZXF1ZXN0MTM0MjQ4ODU5", "number": 1, "title": "Deploy update", "user": {"login": "osowskit", "id": 768821, "node_id": "MDQ6VXNlcjc2ODgyMQ==", "avatar_url": "https://avatars.githubusercontent.com/u/768821?v=4", "gravatar_id": "", "url": "https://api.github.com/users/osowskit", "html_url": "https://github.com/osowskit", "followers_url": "https://api.github.com/users/osowskit/followers", "following_url": "https://api.github.com/users/osowskit/following{/other_user}", "gists_url": "https://api.github.com/users/osowskit/gists{/gist_id}", "starred_url": "https://api.github.com/users/osowskit/starred{/owner}{/repo}", "subscriptions_url": "https://api.github.com/users/osowskit/subscriptions", "organizations_url": "https://api.github.com/users/osowskit/orgs", "repos_url": "https://api.github.com/users/osowskit/repos", "events_url": "https://api.github.com/users/osowskit/events{/privacy}", "received_events_url": "https://api.github.com/users/osowskit/received_events", "type": "User", "site_admin": false}, "labels": [], "state": "closed", "locked": true, "assignee": null, "assignees": [], "milestone": null, "comments": 0, "created_at": "2017-08-04T20:50:12Z", "updated_at": "2017-08-04T20:52:34Z", "closed_at": "2017-08-04T20:52:34Z", "author_association": "OWNER", "active_lock_reason": null, "draft": false, "pull_request": {"url": "https://api.github.com/repos/osowskit/microsoft-github-app-extension/pulls/1", "html_url": "https://github.com/osowskit/microsoft-github-app-extension/pull/1", "diff_url": "https://github.com/osowskit/microsoft-github-app-extension/pull/1.diff", "patch_url": "https://github.com/osowskit/microsoft-github-app-extension/pull/1.patch", "merged_at": "2017-08-04T20:52:34Z"}, "body": "Update from latest.", "reactions": {"url": "https://api.github.com/repos/osowskit/microsoft-github-app-extension/issues/1/reactions", "total_count": 0, "+1": 0, "-1": 0, "laugh": 0, "hooray": 0, "confused": 0, "heart": 0, "rocket": 0, "eyes": 0}, "timeline_url": "https://api.github.com/repos/osowskit/microsoft-github-app-extension/issues/1/timeline", "performed_via_github_app": null, "state_reason": null, "score": 1.0}]}