[{"login": "hotwatermorning", "id": 359226, "node_id": "MDQ6VXNlcjM1OTIyNg==", "avatar_url": "https://avatars.githubusercontent.com/u/359226?v=4", "gravatar_id": "", "url": "https://api.github.com/users/hotwatermorning", "html_url": "https://github.com/hotwatermorning", "followers_url": "https://api.github.com/users/hotwatermorning/followers", "following_url": "https://api.github.com/users/hotwatermorning/following{/other_user}", "gists_url": "https://api.github.com/users/hotwatermorning/gists{/gist_id}", "starred_url": "https://api.github.com/users/hotwatermorning/starred{/owner}{/repo}", "subscriptions_url": "https://api.github.com/users/hotwatermorning/subscriptions", "organizations_url": "https://api.github.com/users/hotwatermorning/orgs", "repos_url": "https://api.github.com/users/hotwatermorning/repos", "events_url": "https://api.github.com/users/hotwatermorning/events{/privacy}", "received_events_url": "https://api.github.com/users/hotwatermorning/received_events", "type": "User", "site_admin": false, "contributions": 63}]