{"sha": "bf211f51fe05ce8890c76291b172a886035ed3d7", "node_id": "MDY6Q29tbWl0MTE1OTA5NDQzOmJmMjExZjUxZmUwNWNlODg5MGM3NjI5MWIxNzJhODg2MDM1ZWQzZDc=", "commit": {"author": {"name": "Allan Hardy", "email": "al_hardy@live.com.au", "date": "2018-02-27T02:50:03Z"}, "committer": {"name": "Allan Hardy", "email": "al_hardy@live.com.au", "date": "2018-02-27T02:50:03Z"}, "message": "updating ensure cosmos db task", "tree": {"sha": "5fa0b0149756233cf8ed8d5544839e16c442a24d", "url": "https://api.github.com/repos/alhardy/vsts-tasks/git/trees/5fa0b0149756233cf8ed8d5544839e16c442a24d"}, "url": "https://api.github.com/repos/alhardy/vsts-tasks/git/commits/bf211f51fe05ce8890c76291b172a886035ed3d7", "comment_count": 0, "verification": {"verified": false, "reason": "unsigned", "signature": null, "payload": null}}, "url": "https://api.github.com/repos/alhardy/vsts-tasks/commits/bf211f51fe05ce8890c76291b172a886035ed3d7", "html_url": "https://github.com/alhardy/vsts-tasks/commit/bf211f51fe05ce8890c76291b172a886035ed3d7", "comments_url": "https://api.github.com/repos/alhardy/vsts-tasks/commits/bf211f51fe05ce8890c76291b172a886035ed3d7/comments", "author": {"login": "alhardy", "id": 729185, "node_id": "MDQ6VXNlcjcyOTE4NQ==", "avatar_url": "https://avatars.githubusercontent.com/u/729185?v=4", "gravatar_id": "", "url": "https://api.github.com/users/alhardy", "html_url": "https://github.com/alhardy", "followers_url": "https://api.github.com/users/alhardy/followers", "following_url": "https://api.github.com/users/alhardy/following{/other_user}", "gists_url": "https://api.github.com/users/alhardy/gists{/gist_id}", "starred_url": "https://api.github.com/users/alhardy/starred{/owner}{/repo}", "subscriptions_url": "https://api.github.com/users/alhardy/subscriptions", "organizations_url": "https://api.github.com/users/alhardy/orgs", "repos_url": "https://api.github.com/users/alhardy/repos", "events_url": "https://api.github.com/users/alhardy/events{/privacy}", "received_events_url": "https://api.github.com/users/alhardy/received_events", "type": "User", "site_admin": false}, "committer": {"login": "alhardy", "id": 729185, "node_id": "MDQ6VXNlcjcyOTE4NQ==", "avatar_url": "https://avatars.githubusercontent.com/u/729185?v=4", "gravatar_id": "", "url": "https://api.github.com/users/alhardy", "html_url": "https://github.com/alhardy", "followers_url": "https://api.github.com/users/alhardy/followers", "following_url": "https://api.github.com/users/alhardy/following{/other_user}", "gists_url": "https://api.github.com/users/alhardy/gists{/gist_id}", "starred_url": "https://api.github.com/users/alhardy/starred{/owner}{/repo}", "subscriptions_url": "https://api.github.com/users/alhardy/subscriptions", "organizations_url": "https://api.github.com/users/alhardy/orgs", "repos_url": "https://api.github.com/users/alhardy/repos", "events_url": "https://api.github.com/users/alhardy/events{/privacy}", "received_events_url": "https://api.github.com/users/alhardy/received_events", "type": "User", "site_admin": false}, "parents": [{"sha": "81393c2421dc23fe2a5e16bb49af7af9865a6f9c", "url": "https://api.github.com/repos/alhardy/vsts-tasks/commits/81393c2421dc23fe2a5e16bb49af7af9865a6f9c", "html_url": "https://github.com/alhardy/vsts-tasks/commit/81393c2421dc23fe2a5e16bb49af7af9865a6f9c"}], "repository": "alhardy/vsts-tasks", "number": "13"}