{"login": "JoergBitzer", "id": 7204623, "node_id": "MDQ6VXNlcjcyMDQ2MjM=", "avatar_url": "https://avatars.githubusercontent.com/u/7204623?v=4", "gravatar_id": "", "url": "https://api.github.com/users/JoergBitzer", "html_url": "https://github.com/JoergBitzer", "followers_url": "https://api.github.com/users/JoergBitzer/followers", "following_url": "https://api.github.com/users/JoergBitzer/following{/other_user}", "gists_url": "https://api.github.com/users/JoergBitzer/gists{/gist_id}", "starred_url": "https://api.github.com/users/JoergBitzer/starred{/owner}{/repo}", "subscriptions_url": "https://api.github.com/users/JoergBitzer/subscriptions", "organizations_url": "https://api.github.com/users/JoergBitzer/orgs", "repos_url": "https://api.github.com/users/JoergBitzer/repos", "events_url": "https://api.github.com/users/JoergBitzer/events{/privacy}", "received_events_url": "https://api.github.com/users/JoergBitzer/received_events", "type": "User", "site_admin": false, "name": "Joerg Bitzer", "company": "Jade Hochschule", "blog": "https://www.jade-hs.de/team/joerg-bitzer/", "location": "Oldenburg, Germany", "email": null, "hireable": null, "bio": null, "twitter_username": null, "public_repos": 28, "public_gists": 0, "followers": 13, "following": 0, "created_at": "2014-04-07T12:31:18Z", "updated_at": "2023-12-08T18:54:07Z"}