{"login": "tparker48", "id": 32755663, "node_id": "MDQ6VXNlcjMyNzU1NjYz", "avatar_url": "https://avatars.githubusercontent.com/u/32755663?v=4", "gravatar_id": "", "url": "https://api.github.com/users/tparker48", "html_url": "https://github.com/tparker48", "followers_url": "https://api.github.com/users/tparker48/followers", "following_url": "https://api.github.com/users/tparker48/following{/other_user}", "gists_url": "https://api.github.com/users/tparker48/gists{/gist_id}", "starred_url": "https://api.github.com/users/tparker48/starred{/owner}{/repo}", "subscriptions_url": "https://api.github.com/users/tparker48/subscriptions", "organizations_url": "https://api.github.com/users/tparker48/orgs", "repos_url": "https://api.github.com/users/tparker48/repos", "events_url": "https://api.github.com/users/tparker48/events{/privacy}", "received_events_url": "https://api.github.com/users/tparker48/received_events", "type": "User", "site_admin": false, "name": "Thomas Parker", "company": "Belcan", "blog": "https://tparker48.github.io/", "location": null, "email": null, "hireable": true, "bio": "Software Engineer\r\n", "twitter_username": null, "public_repos": 20, "public_gists": 0, "followers": 8, "following": 4, "created_at": "2017-10-13T02:02:05Z", "updated_at": "2023-12-01T23:42:27Z"}