{"total_count": 4, "incomplete_results": false, "items": [{"url": "https://api.github.com/repos/elk-audio/sushi/issues/8", "repository_url": "https://api.github.com/repos/elk-audio/sushi", "labels_url": "https://api.github.com/repos/elk-audio/sushi/issues/8/labels{/name}", "comments_url": "https://api.github.com/repos/elk-audio/sushi/issues/8/comments", "events_url": "https://api.github.com/repos/elk-audio/sushi/issues/8/events", "html_url": "https://github.com/elk-audio/sushi/pull/8", "id": 1786011812, "node_id": "PR_kwDODX3x0s5UhG7p", "number": 8, "title": "Fix documentation link", "user": {"login": "laenzlinger", "id": 6319634, "node_id": "MDQ6VXNlcjYzMTk2MzQ=", "avatar_url": "https://avatars.githubusercontent.com/u/6319634?v=4", "gravatar_id": "", "url": "https://api.github.com/users/laenzlinger", "html_url": "https://github.com/laenzlinger", "followers_url": "https://api.github.com/users/laenzlinger/followers", "following_url": "https://api.github.com/users/laenzlinger/following{/other_user}", "gists_url": "https://api.github.com/users/laenzlinger/gists{/gist_id}", "starred_url": "https://api.github.com/users/laenzlinger/starred{/owner}{/repo}", "subscriptions_url": "https://api.github.com/users/laenzlinger/subscriptions", "organizations_url": "https://api.github.com/users/laenzlinger/orgs", "repos_url": "https://api.github.com/users/laenzlinger/repos", "events_url": "https://api.github.com/users/laenzlinger/events{/privacy}", "received_events_url": "https://api.github.com/users/laenzlinger/received_events", "type": "User", "site_admin": false}, "labels": [], "state": "closed", "locked": false, "assignee": null, "assignees": [], "milestone": null, "comments": 1, "created_at": "2023-07-03T11:46:48Z", "updated_at": "2023-07-13T12:35:49Z", "closed_at": "2023-07-13T12:35:48Z", "author_association": "NONE", "active_lock_reason": null, "draft": false, "pull_request": {"url": "https://api.github.com/repos/elk-audio/sushi/pulls/8", "html_url": "https://github.com/elk-audio/sushi/pull/8", "diff_url": "https://github.com/elk-audio/sushi/pull/8.diff", "patch_url": "https://github.com/elk-audio/sushi/pull/8.patch", "merged_at": null}, "body": "Link to sushi documentation seems to be outdated. ", "reactions": {"url": "https://api.github.com/repos/elk-audio/sushi/issues/8/reactions", "total_count": 0, "+1": 0, "-1": 0, "laugh": 0, "hooray": 0, "confused": 0, "heart": 0, "rocket": 0, "eyes": 0}, "timeline_url": "https://api.github.com/repos/elk-audio/sushi/issues/8/timeline", "performed_via_github_app": null, "state_reason": null, "score": 1.0}]}